libalgo/__init__.py
libalgo/core.cp311-win_amd64.pyd
lib_algo_native-1.0.0.dist-info/METADATA
lib_algo_native-1.0.0.dist-info/WHEEL
lib_algo_native-1.0.0.dist-info/top_level.txt
lib_algo_native-1.0.0.dist-info/RECORD
