Metadata-Version: 2.4
Name: lib-algo-native
Version: 1.0.0
Summary: High-performance native C extensions for advanced mathematical algorithms and server computation.
Home-page: https://pypi.org/project/lib-algo-native/
Author: LibAlgo OpenSource Team
Author-email: support@libalgo.org
License: MIT
Classifier: Programming Language :: Python :: 3
Classifier: License :: OSI Approved :: MIT License
Classifier: Operating System :: OS Independent
Classifier: Topic :: Scientific/Engineering :: Mathematics
Dynamic: author
Dynamic: author-email
Dynamic: classifier
Dynamic: home-page
Dynamic: license
Dynamic: summary
